[
  {
    "story": "You fall into a deep sleep on the sand, the sound of the waves helping you drift away. The night is calm and restorative.",
    "hunger": 10,
    "thirst": 10,
    "energy": 20
  },
  {
    "story": "You sleep well despite the wind blowing through the night. In the morning, you feel rested and ready to go.",
    "hunger": 10,
    "thirst": 10,
    "energy": 15
  },
  {
    "story": "You sleep poorly because of the mosquitoes, but still manage to recover a bit of energy.",
    "hunger": 5,
    "thirst": 5,
    "energy": 10
  },
  {
    "story": "The rain wakes you several times during the night, but your body still finds some rest.",
    "hunger": 10,
    "thirst": 10,
    "energy": 10
  },
  {
    "story": "You sleep on the hard, uncomfortable ground. Not ideal, but you regain some strength nonetheless.",
    "hunger": 5,
    "thirst": 10,
    "energy": 10
  },
  {
    "story": "You find shelter under a large tree and spend a surprisingly comfortable night. In the morning, you feel re-energized.",
    "hunger": 10,
    "thirst": 10,
    "energy": 20
  },
  {
    "story": "You sleep lightly, alert to every sound around you. It's not very restful, but better than nothing.",
    "hunger": 5,
    "thirst": 5,
    "energy": 5
  },
  {
    "story": "You fall asleep next to your campfire and rest deeply. The warmth and calm help you recover well.",
    "hunger": 10,
    "thirst": 10,
    "energy": 20
  },
  {
    "story": "You end up sleeping most of the day. You feel much better, though your hunger grows stronger.",
    "hunger": 15,
    "thirst": 15,
    "energy": 20
  },
  {
    "story": "You close your eyes and quickly drift off. You regain your strength, but wake up with an empty stomach.",
    "hunger": 10,
    "thirst": 10,
    "energy": 15
  }
]